[{"id":"8584ebb2-973a-4575-8454-95a3548b6844","status":true,"title":"Pancho","description":"Comida","code":"01","price":1500,"stock":100,"category":"comidas"},{"id":"0eeff25e-9f50-47e3-9146-6420f708ae48","status":true,"title":"Ciruela","description":"Comida","code":"02","price":1500,"stock":100,"category":"comidas"},{"id":"cc8a7fd3-ff9d-47fc-a5ed-f7471208787e","status":true,"title":"Mochila","description":"util","code":"13","price":40400,"stock":3,"category":"escolar"},{"id":"7c1a73ee-2c0b-44c4-8d8b-b7d776aa1020","status":true,"title":"Mochila","description":"util","code":"13","price":40400,"stock":3,"category":"escolar"},{"id":"c8f2037f-f3b6-43a4-aef9-f8f7573978bc","status":true,"title":"Mochila","description":"util","code":"13","price":40400,"stock":3,"category":"escolar"},{"id":"44d2bdaa-d646-4e06-bc74-03c996b28da1","status":true,"title":"Mochila","description":"util","code":"13","price":40400,"stock":3,"category":"escolar"},{"id":"911ea288-b657-44ea-949e-489a51a29fb8","status":true,"title":"Mochila","description":"util","code":"13","price":40400,"stock":3,"category":"escolar"},{"id":"1538d55e-112c-46a2-8822-431039abf58f","status":true,"title":"Mochila","description":"util","code":"13","price":40400,"stock":3,"category":"escolar"},{"id":"b2ca892f-867c-434e-93d1-762254a5d6e9","status":true,"title":"Mochila","description":"util","code":"13","price":40400,"stock":3,"category":"escolar"},{"id":"a3a328a6-41ba-4a18-9ed0-28838f62f8e5","status":true,"title":"Mochila","description":"util","code":"13","price":40400,"stock":3,"category":"escolar"}]